singleton_provider/__init__.py
singleton_provider/decorators.py
singleton_provider/decorators.pyi
singleton_provider/exceptions.py
singleton_provider/provider.py
singleton_provider/_internal/__init__.py
singleton_provider/_internal/_metaclass.py
singleton_provider/_internal/_utils.py
singleton_provider-0.1.1.dist-info/METADATA
singleton_provider-0.1.1.dist-info/WHEEL
singleton_provider-0.1.1.dist-info/licenses/LICENSE
singleton_provider-0.1.1.dist-info/RECORD
